pySailingVLM/__main__.py
pySailingVLM/variables.py
pySailingVLM/examples/rectangle_variables.py
pySailingVLM/examples/sweep_variables.py
pySailingVLM/examples/variables.py
pySailingVLM/inlet/__init__.py
pySailingVLM/inlet/inlet_conditions.py
pySailingVLM/inlet/winds.py
pySailingVLM/results/__init__.py
pySailingVLM/results/inviscid_flow.py
pySailingVLM/results/save_utils.py
pySailingVLM/rotations/__init__.py
pySailingVLM/rotations/csys_transformations.py
pySailingVLM/rotations/geometry_calc.py
pySailingVLM/runner/__init__.py
pySailingVLM/runner/aircraft.py
pySailingVLM/runner/cli.py
pySailingVLM/runner/container.py
pySailingVLM/runner/sail.py
pySailingVLM/solver/__init__.py
pySailingVLM/solver/additional_functions.py
pySailingVLM/solver/coefs.py
pySailingVLM/solver/forces.py
pySailingVLM/solver/interpolator.py
pySailingVLM/solver/mesher.py
pySailingVLM/solver/panels.py
pySailingVLM/solver/panels_plotter.py
pySailingVLM/solver/velocity.py
pySailingVLM/solver/vlm.py
pySailingVLM/thin_airfoil/vlm_airfoil.py
pySailingVLM/yacht_geometry/__init__.py
pySailingVLM/yacht_geometry/hull_geometry.py
pySailingVLM/yacht_geometry/sail_factory.py
pySailingVLM/yacht_geometry/sail_geometry.py
venv/bin/activate_this.py
pySailingVLM-1.0.3.dist-info/LICENSE
pySailingVLM-1.0.3.dist-info/METADATA
pySailingVLM-1.0.3.dist-info/WHEEL
pySailingVLM-1.0.3.dist-info/entry_points.txt
pySailingVLM-1.0.3.dist-info/top_level.txt
pySailingVLM-1.0.3.dist-info/zip-safe
pySailingVLM-1.0.3.dist-info/RECORD
