Metadata-Version: 2.1
Name: pySailingVLM
Version: 1.0.3
Summary: 'Vortex Lattice Method for initial aerodynamic analysis of upwind sails.'
Home-page: https://orgsailingvlm.github.io/vlmbook
Author: Grzegorz Gruszczynski, Zuzanna Wieczorek
Keywords: Vortex Lattice Method,VLM,initial sail analysis,yacht engineering
Classifier: License :: OSI Approved :: Apache Software License
Classifier: Programming Language :: Python :: 3
Classifier: Programming Language :: Python :: 3.10
Classifier: Topic :: Software Development
Classifier: Topic :: Scientific/Engineering :: Information Analysis
Classifier: Topic :: Scientific/Engineering :: Visualization
Classifier: Topic :: Scientific/Engineering :: Physics
Classifier: Topic :: Education
Classifier: Framework :: Jupyter
Classifier: Intended Audience :: End Users/Desktop
Classifier: Intended Audience :: Developers
Classifier: Intended Audience :: Education
Classifier: Intended Audience :: Science/Research
Classifier: Operating System :: POSIX :: Linux
License-File: LICENSE
Requires-Dist: numba
Requires-Dist: numpy
Requires-Dist: matplotlib
Requires-Dist: scipy
Requires-Dist: pandas
Requires-Dist: openpyxl
Requires-Dist: xlsxwriter
Requires-Dist: holoviews
Requires-Dist: spatialpandas
Requires-Dist: ipympl ==0.9.3
Requires-Dist: ipywidgets ==8.0.4
Requires-Dist: jupyterlab ==3.6.3
